emuemuJP/__init__.py
emuemuJP/pointcloud/__init__.py
emuemuJP/pointcloud/io.py
emuemuJP/pointcloud/measure.py
emuemuJP/pointcloud/process.py
emuemuJP/pointcloud/visualization.py
emuemuJP/pointcloud/visualize.py
tests/__init__.py
emuemuJP-0.0.6.dist-info/LICENSE.txt
emuemuJP-0.0.6.dist-info/METADATA
emuemuJP-0.0.6.dist-info/WHEEL
emuemuJP-0.0.6.dist-info/top_level.txt
emuemuJP-0.0.6.dist-info/RECORD
