Metadata-Version: 2.1
Name: emuemuJP
Version: 0.0.6
Summary: This is a package for me.
Author: emuemuJP
Author-email: k.matsumoto.0807@gmail.com
Classifier: License :: OSI Approved :: MIT License
Classifier: Programming Language :: Python :: 3.6
Classifier: Programming Language :: Python :: 3.7
Classifier: Programming Language :: Python :: 3.8
Classifier: Operating System :: OS Independent
Requires-Python: ~=3.6
License-File: LICENSE.txt
Requires-Dist: twine (>=3.8.0)
Requires-Dist: wheel (>=0.37.1)
